oobfuzz/__init__.py
oobfuzz/__main__.py
oobfuzz/data/user-agents.txt
oobfuzz/data/payloads/openredir.txt
oobfuzz/data/payloads/rce.txt
oobfuzz/data/payloads/sqli.txt
oobfuzz/data/payloads/ssrf.txt
oobfuzz/data/payloads/xxs.txt
OOB_Fuzz-0.1.0.dist-info/LICENSE
OOB_Fuzz-0.1.0.dist-info/METADATA
OOB_Fuzz-0.1.0.dist-info/WHEEL
OOB_Fuzz-0.1.0.dist-info/top_level.txt
OOB_Fuzz-0.1.0.dist-info/RECORD
