Metadata-Version: 2.1
Name: OOB-Fuzz
Version: 0.1.0
Summary: Conduct OOB Fuzzing of targets with payloads towards callback server
Home-page: https://github.com/CasperGN/oobfuzz
Author: Casper G. Nielsen
Author-email: whopsec@protonmail.com
License: UNKNOWN
Platform: UNKNOWN
Classifier: Programming Language :: Python :: 3
Classifier: License :: OSI Approved :: MIT License
Requires-Python: >=3.4
Requires-Dist: requests
Requires-Dist: pyopenssl
Requires-Dist: cffi
